pint_lib/__init__.py
pint_lib/__main__.py
pint_lib/claude_engine.py
pint_lib/external_engine.py
pint_lib/main.py
pint_lib/model_data.py
pint_lib/open_ai_engine.py
pint_lib/parse_papers.py
pint_lib/parse_pubmed_json.py
pint_lib/prompt_cache.py
pint_lib/prompt_cache_sqlite.py
pint_lib/prompt_data.py
pint_lib/requirements.txt
pint_lib/run_pint.py
pint_lib/test_gpt.py
pint_lib-0.2.9.dist-info/METADATA
pint_lib-0.2.9.dist-info/WHEEL
pint_lib-0.2.9.dist-info/licenses/LICENSE
pint_lib-0.2.9.dist-info/RECORD
