Metadata-Version: 2.4
Name: pint_lib
Version: 0.2.9
Summary: A package for automated processing of (pubmed) text with LLM
Project-URL: Homepage, https://github.com/tonyatliv/Pint/
Project-URL: Issues, https://github.com/tonyatliv/Pint/issues
Author-email: Antony McCabe <a.mccabe@liverpool.ac.uk>
License-Expression: MIT
License-File: LICENSE
Classifier: Operating System :: OS Independent
Classifier: Programming Language :: Python :: 3
Requires-Python: >=3.5
Requires-Dist: anthropic
Requires-Dist: openai
Requires-Dist: openpyxl
Requires-Dist: pdfminer-six
Requires-Dist: requests
Provides-Extra: base
